pywarera/__init__.py
pywarera/core.py
pywarera/wareraapi.py
pywarera/classes/Company.py
pywarera/classes/Country.py
pywarera/classes/CountryRanking.py
pywarera/classes/CountryRankings.py
pywarera/classes/GameConfig.py
pywarera/classes/Government.py
pywarera/classes/Item.py
pywarera/classes/ItemPrices.py
pywarera/classes/ItemsConfig.py
pywarera/classes/MilitaryUnit.py
pywarera/classes/Region.py
pywarera/classes/User.py
pywarera/classes/UserDates.py
pywarera/classes/UserLeveling.py
pywarera/classes/UserRanking.py
pywarera/classes/UserRankings.py
pywarera/classes/UserSkill.py
pywarera/classes/UserSkillBar.py
pywarera/classes/UserSkills.py
pywarera/classes/__init__.py
pywarera-0.2.0.dist-info/licenses/LICENSE
pywarera-0.2.0.dist-info/METADATA
pywarera-0.2.0.dist-info/WHEEL
pywarera-0.2.0.dist-info/top_level.txt
pywarera-0.2.0.dist-info/RECORD
