Metadata-Version: 2.4
Name: pywarera
Version: 0.2.0
Summary: WarEra browser game API wrapper
Author: Marerjh
License-Expression: GPL-3.0-only
Project-URL: Homepage, https://github.com/Marerjh/pywarera
Project-URL: Issues, https://github.com/Marerjh/pywarera/issues
Classifier: Programming Language :: Python :: 3
Classifier: Operating System :: OS Independent
Classifier: Development Status :: 3 - Alpha
Classifier: Intended Audience :: Developers
Requires-Python: >=3.10
License-File: LICENSE
Requires-Dist: requests==2.32.5
Requires-Dist: requests-cache==1.2.1
Dynamic: license-file
